backupr/__init__.py
backupr/cli.py
backupr/config.py
backupr/di.py
backupr/encrypter.py
backupr/engine.py
backupr/storage_provider/__init__.py
backupr/storage_provider/b2_provider.py
backupr/storage_provider/local_provider.py
backupr/tar_builder.py
backupr/util.py
nsk_backupr-0.2.1.dist-info/LICENSE
nsk_backupr-0.2.1.dist-info/METADATA
nsk_backupr-0.2.1.dist-info/WHEEL
nsk_backupr-0.2.1.dist-info/entry_points.txt
nsk_backupr-0.2.1.dist-info/RECORD
